natmlx/__init__.py
natmlx/template.py
natmlx/utils.py
natmlx/version.py
natmlx/templates/edge_unity/LICENSE
natmlx/templates/edge_unity/LICENSE.meta
natmlx/templates/edge_unity/ML.meta
natmlx/templates/edge_unity/README.md
natmlx/templates/edge_unity/README.md.meta
natmlx/templates/edge_unity/Runtime.meta
natmlx/templates/edge_unity/Sample.meta
natmlx/templates/edge_unity/predictor.meta
natmlx/templates/edge_unity/Runtime/CLASS_NAME.asmdef
natmlx/templates/edge_unity/Runtime/CLASS_NAME.asmdef.meta
natmlx/templates/edge_unity/Runtime/CLASS_NAMEPredictor.cs
natmlx/templates/edge_unity/Runtime/CLASS_NAMEPredictor.cs.meta
natmlx/templates/edge_unity/Sample/CLASS_NAMESample.cs
natmlx/templates/edge_unity/Sample/CLASS_NAMESample.cs.meta
natmlx/templates/edge_unity/Sample/CLASS_NAMESample.unity
natmlx/templates/edge_unity/Sample/CLASS_NAMESample.unity.meta
natmlx/templates/hub_node/.env.example
natmlx/templates/hub_node/.gitignore
natmlx/templates/hub_node/README.md
natmlx/templates/hub_node/package.json
natmlx/templates/hub_node/tsconfig.json
natmlx/templates/hub_node/src/CLASS_NAMEPredictor.ts
natmlx/templates/hub_node/src/index.ts
natmlx/templates/hub_node/test/sample.ts
natmlx/templates/hub_python/README.md
natmlx/templates/hub_unity/LICENSE
natmlx/templates/hub_unity/LICENSE.meta
natmlx/templates/hub_unity/ML.meta
natmlx/templates/hub_unity/README.md
natmlx/templates/hub_unity/README.md.meta
natmlx/templates/hub_unity/Runtime.meta
natmlx/templates/hub_unity/Sample.meta
natmlx/templates/hub_unity/predictor.meta
natmlx/templates/hub_unity/Runtime/CLASS_NAME.asmdef
natmlx/templates/hub_unity/Runtime/CLASS_NAME.asmdef.meta
natmlx/templates/hub_unity/Runtime/CLASS_NAMEPredictor.cs
natmlx/templates/hub_unity/Runtime/CLASS_NAMEPredictor.cs.meta
natmlx/templates/hub_unity/Sample/CLASS_NAMESample.cs
natmlx/templates/hub_unity/Sample/CLASS_NAMESample.cs.meta
natmlx/templates/hub_unity/Sample/CLASS_NAMESample.unity
natmlx/templates/hub_unity/Sample/CLASS_NAMESample.unity.meta
natmlx-0.0.5.dist-info/LICENSE
natmlx-0.0.5.dist-info/METADATA
natmlx-0.0.5.dist-info/WHEEL
natmlx-0.0.5.dist-info/entry_points.txt
natmlx-0.0.5.dist-info/top_level.txt
natmlx-0.0.5.dist-info/RECORD
