Metadata-Version: 2.1
Name: natmlx
Version: 0.0.5
Summary: Machine learning extensions for Python.
Home-page: https://natml.ai
Author: NatML
Author-email: hi@natml.ai
License: Apache License 2.0
Project-URL: Documentation, https://docs.natml.ai/python
Project-URL: Source, https://github.com/natsuite/NatMLX-Py
Platform: UNKNOWN
Classifier: Programming Language :: Python :: 3
Classifier: License :: OSI Approved :: Apache Software License
Classifier: Operating System :: OS Independent
Classifier: Topic :: Software Development :: Libraries
Requires-Python: >=3.6
Requires-Dist: path
Requires-Dist: pyyaml
